{"metadata": {"dbt_schema_version": "https://schemas.getdbt.com/dbt/run-results/v4.json", "dbt_version": "1.4.5", "generated_at": "2023-03-27T13:43:11.474726Z", "invocation_id": "20d40d65-3e4f-41c4-a5bf-9597d340fd5a", "env": {}}, "results": [{"status": "success", "timing": [{"name": "compile", "started_at": "2023-03-27T13:43:11.148822Z", "completed_at": "2023-03-27T13:43:11.166703Z"}, {"name": "execute", "started_at": "2023-03-27T13:43:11.171063Z", "completed_at": "2023-03-27T13:43:11.171147Z"}], "thread_id": "Thread-1 (worker)", "execution_time": 0.031204938888549805, "adapter_response": {}, "message": null, "failures": null, "unique_id": "model.mark.marketing_first_model"}, {"status": "success", "timing": [{"name": "compile", "started_at": "2023-03-27T13:43:11.207759Z", "completed_at": "2023-03-27T13:43:11.294439Z"}, {"name": "execute", "started_at": "2023-03-27T13:43:11.301711Z", "completed_at": "2023-03-27T13:43:11.301767Z"}], "thread_id": "Thread-3 (worker)", "execution_time": 0.11633515357971191, "adapter_response": {}, "message": null, "failures": null, "unique_id": "model.fina.finance_first_model"}, {"status": "success", "timing": [{"name": "compile", "started_at": "2023-03-27T13:43:11.221671Z", "completed_at": "2023-03-27T13:43:11.295499Z"}, {"name": "execute", "started_at": "2023-03-27T13:43:11.305012Z", "completed_at": "2023-03-27T13:43:11.305053Z"}], "thread_id": "Thread-4 (worker)", "execution_time": 0.1173851490020752, "adapter_response": {}, "message": null, "failures": null, "unique_id": "model.mark.marketing_second_model"}, {"status": "success", "timing": [{"name": "compile", "started_at": "2023-03-27T13:43:11.237298Z", "completed_at": "2023-03-27T13:43:11.299166Z"}, {"name": "execute", "started_at": "2023-03-27T13:43:11.309962Z", "completed_at": "2023-03-27T13:43:11.309991Z"}], "thread_id": "Thread-5 (worker)", "execution_time": 0.11997699737548828, "adapter_response": {}, "message": null, "failures": null, "unique_id": "test.mark.unique_marketing_first_model_id.9d1dc805ac"}, {"status": "success", "timing": [{"name": "compile", "started_at": "2023-03-27T13:43:11.340950Z", "completed_at": "2023-03-27T13:43:11.431484Z"}, {"name": "execute", "started_at": "2023-03-27T13:43:11.440116Z", "completed_at": "2023-03-27T13:43:11.440184Z"}], "thread_id": "Thread-7 (worker)", "execution_time": 0.12161993980407715, "adapter_response": {}, "message": null, "failures": null, "unique_id": "test.fina.unique_finance_first_model_id.7cafc8c11d"}, {"status": "success", "timing": [{"name": "compile", "started_at": "2023-03-27T13:43:11.379072Z", "completed_at": "2023-03-27T13:43:11.434184Z"}, {"name": "execute", "started_at": "2023-03-27T13:43:11.443595Z", "completed_at": "2023-03-27T13:43:11.443628Z"}], "thread_id": "Thread-1 (worker)", "execution_time": 0.11917972564697266, "adapter_response": {}, "message": null, "failures": null, "unique_id": "test.mark.unique_marketing_second_model_ID.180ff0615f"}, {"status": "success", "timing": [{"name": "compile", "started_at": "2023-03-27T13:43:11.358044Z", "completed_at": "2023-03-27T13:43:11.436684Z"}, {"name": "execute", "started_at": "2023-03-27T13:43:11.448542Z", "completed_at": "2023-03-27T13:43:11.448576Z"}], "thread_id": "Thread-2 (worker)", "execution_time": 0.1273648738861084, "adapter_response": {}, "message": null, "failures": null, "unique_id": "test.mark.not_null_marketing_second_model_ID.4f2242678d"}], "elapsed_time": 0.780681848526001, "args": {"write_json": true, "use_colors": true, "printer_width": 80, "version_check": true, "partial_parse": true, "static_parser": true, "profiles_dir": "/root/.dbt", "send_anonymous_usage_stats": true, "quiet": false, "no_print": false, "cache_selected_only": false, "parse_only": false, "which": "compile", "rpc_method": "compile", "indirect_selection": "eager"}}