{"metadata": {"dbt_schema_version": "https://schemas.getdbt.com/dbt/run-results/v4.json", "dbt_version": "1.4.1", "generated_at": "2023-03-06T16:06:20.975053Z", "invocation_id": "f495989e-ba19-42c1-8c4d-e83a13d19ad7", "env": {}}, "results": [{"status": "success", "timing": [{"name": "compile", "started_at": "2023-03-06T16:06:20.534982Z", "completed_at": "2023-03-06T16:06:20.560164Z"}, {"name": "execute", "started_at": "2023-03-06T16:06:20.568003Z", "completed_at": "2023-03-06T16:06:20.568086Z"}], "thread_id": "Thread-1 (worker)", "execution_time": 0.0471193790435791, "adapter_response": {}, "message": null, "failures": null, "unique_id": "model.mark.marketing_first_model"}, {"status": "success", "timing": [{"name": "compile", "started_at": "2023-03-06T16:06:20.617470Z", "completed_at": "2023-03-06T16:06:20.715393Z"}, {"name": "execute", "started_at": "2023-03-06T16:06:20.732824Z", "completed_at": "2023-03-06T16:06:20.732869Z"}], "thread_id": "Thread-3 (worker)", "execution_time": 0.15158748626708984, "adapter_response": {}, "message": null, "failures": null, "unique_id": "model.fina.finance_first_model"}, {"status": "success", "timing": [{"name": "compile", "started_at": "2023-03-06T16:06:20.633577Z", "completed_at": "2023-03-06T16:06:20.718174Z"}, {"name": "execute", "started_at": "2023-03-06T16:06:20.739006Z", "completed_at": "2023-03-06T16:06:20.739059Z"}], "thread_id": "Thread-4 (worker)", "execution_time": 0.15569138526916504, "adapter_response": {}, "message": null, "failures": null, "unique_id": "model.mark.marketing_second_model"}, {"status": "success", "timing": [{"name": "compile", "started_at": "2023-03-06T16:06:20.650063Z", "completed_at": "2023-03-06T16:06:20.728365Z"}, {"name": "execute", "started_at": "2023-03-06T16:06:20.748604Z", "completed_at": "2023-03-06T16:06:20.748649Z"}], "thread_id": "Thread-2 (worker)", "execution_time": 0.16020846366882324, "adapter_response": {}, "message": null, "failures": null, "unique_id": "test.mark.unique_marketing_first_model_id.9d1dc805ac"}, {"status": "success", "timing": [{"name": "compile", "started_at": "2023-03-06T16:06:20.797642Z", "completed_at": "2023-03-06T16:06:20.896461Z"}, {"name": "execute", "started_at": "2023-03-06T16:06:20.914097Z", "completed_at": "2023-03-06T16:06:20.914145Z"}], "thread_id": "Thread-1 (worker)", "execution_time": 0.16556310653686523, "adapter_response": {}, "message": null, "failures": null, "unique_id": "test.fina.unique_finance_first_model_id.7cafc8c11d"}, {"status": "success", "timing": [{"name": "compile", "started_at": "2023-03-06T16:06:20.820055Z", "completed_at": "2023-03-06T16:06:20.913110Z"}, {"name": "execute", "started_at": "2023-03-06T16:06:20.926934Z", "completed_at": "2023-03-06T16:06:20.926987Z"}], "thread_id": "Thread-3 (worker)", "execution_time": 0.1630089282989502, "adapter_response": {}, "message": null, "failures": null, "unique_id": "test.mark.not_null_marketing_second_model_ID.4f2242678d"}, {"status": "success", "timing": [{"name": "compile", "started_at": "2023-03-06T16:06:20.853514Z", "completed_at": "2023-03-06T16:06:20.908415Z"}, {"name": "execute", "started_at": "2023-03-06T16:06:20.930804Z", "completed_at": "2023-03-06T16:06:20.930858Z"}], "thread_id": "Thread-4 (worker)", "execution_time": 0.16413569450378418, "adapter_response": {}, "message": null, "failures": null, "unique_id": "test.mark.unique_marketing_second_model_ID.180ff0615f"}], "elapsed_time": 4.0086963176727295, "args": {"write_json": true, "use_colors": true, "printer_width": 80, "version_check": true, "partial_parse": true, "static_parser": true, "profiles_dir": "/root/.dbt", "send_anonymous_usage_stats": true, "quiet": false, "no_print": false, "cache_selected_only": false, "compile": true, "which": "generate", "rpc_method": "docs.generate", "indirect_selection": "eager"}}